setup.py
nexuspy/__init__.py
nexuspy/nexus.py
nexuspy.egg-info/PKG-INFO
nexuspy.egg-info/SOURCES.txt
nexuspy.egg-info/dependency_links.txt
nexuspy.egg-info/requires.txt
nexuspy.egg-info/top_level.txt