Metadata-Version: 1.0
Name: nexuspy
Version: 0.1.0
Summary: Wrapper for (parts of) the Nexus Repository API
Home-page: http://github.com/Gohla/nexuspy
Author: Gabriel Konat
Author-email: g.d.p.konat@tudelft.nl
License: Apache 2.0
Platform: UNKNOWN
